frasco/__init__.py
frasco/__main__.py
frasco/app.py
frasco/cli.py
frasco/config.py
frasco/ctx.py
frasco/ext.py
frasco/geoip.py
frasco/helpers.py
frasco/i18n.py
frasco/json_provider.py
frasco/logging.py
frasco/marshaller.py
frasco/request_params.py
frasco/utils.py
frasco/api/__init__.py
frasco/api/auth.py
frasco/api/errors.py
frasco/api/service.py
frasco/api/spec.py
frasco/api/templates/doc.html
frasco/assets/__init__.py
frasco/assets/flask_assets.py
frasco/assets/macros.html
frasco/assets/service-worker.js
frasco/assets/sw_cache.py
frasco/babel/__init__.py
frasco/babel/cli.py
frasco/babel/ctx.py
frasco/babel/extract.py
frasco/babel/signals.py
frasco/babel/user.py
frasco/billing/__init__.py
frasco/billing/eu_vat/__init__.py
frasco/billing/eu_vat/data.py
frasco/billing/eu_vat/model.py
frasco/billing/eu_vat/service.py
frasco/billing/invoicing/__init__.py
frasco/billing/invoicing/model.py
frasco/billing/invoicing/emails/failed_invoice.html
frasco/billing/invoicing/emails/invoice.html
frasco/billing/stripe/__init__.py
frasco/billing/stripe/invoice.py
frasco/billing/stripe/model.py
frasco/billing/stripe/signals.py
frasco/billing/stripe/webhook.py
frasco/billing/stripe/emails/trial_will_end.txt
frasco/mail/__init__.py
frasco/mail/message.py
frasco/mail/provider.py
frasco/mail/providers/__init__.py
frasco/mail/providers/mailgun.py
frasco/mail/providers/smtp.py
frasco/mail/templates/layout.html
frasco/mail/templates/layouts/MAILGUN_LICENSE
frasco/mail/templates/layouts/MAILGUN_README.md
frasco/mail/templates/layouts/alert.html
frasco/mail/templates/layouts/base.html
frasco/mail/templates/layouts/invoice.html
frasco/mail/templates/layouts/macros.html
frasco/mail/templates/layouts/markdown.html
frasco/mail/templates/layouts/text.html
frasco/models/__init__.py
frasco/models/cache.py
frasco/models/decorators.py
frasco/models/ext.py
frasco/models/serializer.py
frasco/models/transactions.py
frasco/models/utils.py
frasco/push/__init__.py
frasco/push/exposed_signals.py
frasco-4.1.2.dist-info/METADATA
frasco-4.1.2.dist-info/WHEEL
frasco-4.1.2.dist-info/entry_points.txt
frasco-4.1.2.dist-info/top_level.txt
frasco-4.1.2.dist-info/RECORD
