Metadata-Version: 2.4
Name: Frasco
Version: 4.1.2
Summary: Set of extensions for Flask to develop SaaS applications
Author-email: Maxime Bouroumeau-Fuseau <maxime.bouroumeau@gmail.com>
Maintainer-email: Digicoop <contact@digicoop.io>
License: MIT
Project-URL: Source Code, https://github.com/digicoop/frasco/
Project-URL: Issue Tracker, https://github.com/digicoop/frasco/issues/
Project-URL: Twitter, https://twitter.com/digicoop
Requires-Python: >=3.10
Requires-Dist: ago~=0.0.95
Requires-Dist: apispec~=6.6.1
Requires-Dist: authlib~=1.6.0
Requires-Dist: boto3~=1.35.26
Requires-Dist: eventlet~=0.37.0
Requires-Dist: Flask~=3.0.3
Requires-Dist: Flask-Babel~=4.0.0
Requires-Dist: Bcrypt-Flask~=1.0.2
Requires-Dist: Flask-Login~=0.6.3
Requires-Dist: Flask-Mail~=0.10.0
Requires-Dist: Flask-Migrate~=4.0.7
Requires-Dist: Flask-RQ2~=18.3
Requires-Dist: Flask-SQLAlchemy==3.0.5
Requires-Dist: SQLAlchemy==1.4.54
Requires-Dist: Flask-WTF~=1.2.1
Requires-Dist: geoip2~=4.8.0
Requires-Dist: glob2~=0.7.0
Requires-Dist: inflection~=0.5.1
Requires-Dist: jinja-layout~=0.4
Requires-Dist: jinja-macro-tags~=0.2
Requires-Dist: Markdown~=3.7
Requires-Dist: premailer~=3.10.0
Requires-Dist: psycopg2-binary~=2.9.9
Requires-Dist: pyotp~=2.9.0
Requires-Dist: python-dateutil~=2.9.0
Requires-Dist: python-slugify~=8.0.4
Requires-Dist: python-socketio~=5.11.4
Requires-Dist: PyYAML~=6.0.2
Requires-Dist: redis~=5.0.8
Requires-Dist: requests~=2.32.3
Requires-Dist: rq~=1.16.2
Requires-Dist: speaklater~=1.3
Requires-Dist: stripe~=10.12.0
Requires-Dist: suds~=1.2.0
Requires-Dist: webassets~=2.0.0
Requires-Dist: uvicorn~=0.32.0
